alu.v
module alu (
  input wire [31:0] a,
  input wire [31:0] b,
  input wire [3:0] alu_ctrl,
  output reg [31:0] result,
  output wire zero
);

  always @(*) begin
    case (alu_ctrl)
      4'b0000: result = a & b;  // AND
      4'b0001: result = a | b;  // OR
      4'b0010: result = a + b;  // ADD
      4'b0110: result = a - b;  // SUB
      4'b0111: result = ($signed(a) < $signed(b)) ? 32'd1 : 32'd0; // SLT
      default: result = 32'd0;  // Fallback for invalid control
    endcase
  end

  assign zero = (result == 0);

endmodule

alu_control.v
module alu_control (
  input wire [6:0] opcode,
  input wire [2:0] funct3,
  input wire [6:0] funct7,
  output reg [3:0] alu_ctrl_out
);

  always @(*) begin
    case (opcode)

      // ----------------------
      // R-type Instructions
      // ----------------------
      7'b0110011: begin
        case ({funct7, funct3})
          10'b0000000000: alu_ctrl_out = 4'b0010; // add
          10'b0100000000: alu_ctrl_out = 4'b0110; // sub
          10'b0000000111: alu_ctrl_out = 4'b0000; // and
          10'b0000000110: alu_ctrl_out = 4'b0001; // or
          10'b0000000010: alu_ctrl_out = 4'b0111; // slt
          default:        alu_ctrl_out = 4'b1111; // invalid
        endcase
      end

      // ----------------------
      // I-type Instructions
      // ----------------------
      7'b0010011: begin
        case (funct3)
          3'b000: alu_ctrl_out = 4'b0010; // addi
          3'b111: alu_ctrl_out = 4'b0000; // andi
          3'b110: alu_ctrl_out = 4'b0001; // ori
          3'b010: alu_ctrl_out = 4'b0111; // slti
          default: alu_ctrl_out = 4'b1111; // invalid
        endcase
      end

      // ----------------------
      // Unknown Opcode
      // ----------------------
      default: begin
        alu_ctrl_out = 4'b1111;
      end

    endcase
  end

endmodule

imm_generator.v
module imm_generator (
  input wire [31:0] instruction,
  output reg [31:0] imm_out
);

  wire [6:0] opcode = instruction[6:0];
  wire [2:0] funct3 = instruction[14:12];

  always @(*) begin
    case (opcode)

      // -------------------------
      // I-type: addi, andi, ori, slti
      // -------------------------
      7'b0010011: begin
        case (funct3)
          3'b001: begin
            imm_out = {27'b0, instruction[24:20]};
          end
          default: begin
            imm_out = {{20{instruction[31]}}, instruction[31:20]};
          end
        endcase
      end

      // -------------------------
      // J-type: jal
      // -------------------------
      7'b1101111: begin
        imm_out = {
          {12{instruction[31]}},            // sign-extend
          instruction[19:12],               // imm[19:12]
          instruction[20],                  // imm[11]
          instruction[30:21],               // imm[10:1]
          1'b0                              // imm[0] (always 0)
        };
      end

      // --------------
      // Default:
      // --------------
      default: begin
        imm_out = 32'b0;
      end

    endcase
  end

endmodule

register_file.v
module register_file (
  input wire clk,
  input wire [4:0] rs1,
  input wire [4:0] rs2,
  input wire [4:0] rd,
  input wire RegWrite,
  input wire [31:0] write_data,
  output wire [31:0] read_data1,
  output wire [31:0] read_data2
);

  reg [31:0] regs[0:31];

  // Read ports (combinational)
  assign read_data1 = (rs1 != 0) ? regs[rs1] : 32'b0;
  assign read_data2 = (rs2 != 0) ? regs[rs2] : 32'b0;

  // Write port (synchronous)
  always @(posedge clk) begin
    if (RegWrite && rd != 0) begin
      regs[rd] <= write_data;
    end
    regs[0] <= 32'b0; // x0 always zero
  end

endmodule

control_unit.v
module control_unit (
  input wire [6:0] opcode,
  output reg RegWrite,
  output reg ALUSrc,
  output reg Jump
);

  always @(*) begin
    // Default values
    RegWrite = 0;
    ALUSrc   = 0;
    Jump     = 0;

    case (opcode)
      7'b0110011: begin // R-type
        RegWrite = 1;
        ALUSrc   = 0;
        Jump     = 0;
      end

      7'b0010011: begin // I-type (e.g., addi)
        RegWrite = 1;
        ALUSrc   = 1;
        Jump     = 0;
      end

      7'b1101111: begin // J-type (jal)
        RegWrite = 1;
        ALUSrc   = 0; // not used in jal
        Jump     = 1;
      end

      default: begin
        RegWrite = 0;
        ALUSrc   = 0;
        Jump     = 0;
      end
    endcase
  end

endmodule

instruction_memory.v
module instruction_memory (
  input wire [31:0] addr,
  output wire [31:0] instruction
);

  reg [31:0] memory [0:255];  // 1 KB memory, 256 words

  initial begin
    $readmemh("instructions.mem", memory);
  end

  // Word-aligned access: use bits [9:2] of address (ignore lower 2 bits)
  assign instruction = memory[addr[9:2]];  
endmodule

riscv_top.v
module riscv_top (
  input wire clk,
  input wire reset
);

  reg [31:0] pc;
  wire [31:0] instruction;
  wire [6:0] opcode;
  wire [4:0] rd, rs1, rs2;
  wire [2:0] funct3;
  wire [6:0] funct7;
  wire [31:0] immediate;

  wire [31:0] reg_data1, reg_data2;
  wire [31:0] alu_result;
  wire [31:0] write_back_data;
  wire [31:0] alu_operand_b;

  wire ctrl_RegWrite, ctrl_ALUSrc, ctrl_Jump;
  wire [3:0] alu_control;

  wire [31:0] next_pc = pc + 32'd4;

  // ================================
  // PROGRAM COUNTER
  // ================================
  always @(posedge clk or posedge reset) begin
    if (reset)
      pc <= 32'b0;
    else if (ctrl_Jump)
      pc <= pc + immediate;  // for jal
    else
      pc <= next_pc;
  end

  // ================================
  // INSTRUCTION MEMORY
  // ================================
  instruction_memory imem_unit (
    .addr(pc),
    .instruction(instruction)
  );

  assign opcode = instruction[6:0];
  assign rd     = instruction[11:7];
  assign funct3 = instruction[14:12];
  assign rs1    = instruction[19:15];
  assign rs2    = instruction[24:20];
  assign funct7 = instruction[31:25];

  // ================================
  // CONTROL UNIT
  // ================================
  control_unit ctrl_unit (
    .opcode(opcode),
    .RegWrite(ctrl_RegWrite),
    .ALUSrc(ctrl_ALUSrc),
    .Jump(ctrl_Jump)
  );

  // ================================
  // REGISTER FILE
  // ================================
  register_file regf_unit (
    .clk(clk),
    .rs1(rs1),
    .rs2(rs2),
    .rd(rd),
    .RegWrite(ctrl_RegWrite),
    .write_data(write_back_data),
    .read_data1(reg_data1),
    .read_data2(reg_data2)
  );

  // ================================
  // IMMEDIATE GENERATOR
  // ================================
  imm_generator immgen_unit (
    .instruction(instruction),
    .imm_out(immediate)
  );

  // ================================
  // ALU CONTROL UNIT
  // ================================
  alu_control aluctrl_unit (
    .opcode(opcode),
    .funct3(funct3),
    .funct7(funct7),
    .alu_ctrl_out(alu_control)
  );

  assign alu_operand_b = ctrl_ALUSrc ? immediate : reg_data2;

  // ================================
  // ALU
  // ================================
  alu alu_unit (
    .a(reg_data1),
    .b(alu_operand_b),
    .alu_ctrl(alu_control),
    .result(alu_result),
    .zero()
  );

  // ================================
  // WRITE BACK
  // ================================
  assign write_back_data = ctrl_Jump ? next_pc : alu_result;
endmodule

riscv_top_tb.v
`timescale 1ns / 1ps

module riscv_top_tb;

  reg clk;
  reg reset;

  // Instantiate the RISC-V top module
  riscv_top dut (
    .clk(clk),
    .reset(reset)
  );

  // Clock generation
  initial begin
    clk = 0;
    forever #5 clk = ~clk; // 10ns clock period
  end

  // Simulation control
  initial begin
    // Dump setup for GTKWave
    $dumpfile("riscywave.vcd");
    $dumpvars(0, riscv_top_tb);

    // Reset sequence
    reset = 1;
    #10 reset = 0;

    // Print header
    $display("\n=== Instruction Execution Trace ===");

    $monitor("Time: %0dns | PC: %08h | Instr: %08h | rd: x%0d | wb_data: %0d",
         $time, dut.pc, dut.instruction, dut.rd, dut.write_back_data);

    // Run simulation
    #300;

    // Final register dump
    $display("\n==== Register File Dump After Execution ====");
    $display("x0  = %0d", dut.regf_unit.regs[0]);
    $display("x1  = %0d", dut.regf_unit.regs[1]);
    $display("x2  = %0d", dut.regf_unit.regs[2]);
    $display("x3  = %0d", dut.regf_unit.regs[3]);
    $display("x4  = %0d", dut.regf_unit.regs[4]);
    $display("x5  = %0d", dut.regf_unit.regs[5]);
    $display("x6  = %0d", dut.regf_unit.regs[6]);
    $display("x7  = %0d", dut.regf_unit.regs[7]);
    $display("x8  = %0d", dut.regf_unit.regs[8]);
    $display("x9  = %0d", dut.regf_unit.regs[9]);
    $display("x10 = %0d", dut.regf_unit.regs[10]);
    $display("x11 = %0d", dut.regf_unit.regs[11]);
    $display("x12 = %0d", dut.regf_unit.regs[12]);
    $display("x13 = %0d", dut.regf_unit.regs[13]);

    $display("==================Finishing=================\n");
    $finish;
  end

endmodule

riscywave.vcd
$date
	Sun Jul 13 11:50:39 2025
$end
$version
	Icarus Verilog
$end
$timescale
	1ps
$end
$scope module riscv_top_tb $end
$var reg 1 ! clk $end
$var reg 1 " reset $end
$scope module dut $end
$var wire 1 ! clk $end
$var wire 1 " reset $end
$var wire 32 # write_back_data [31:0] $end
$var wire 5 $ rs2 [4:0] $end
$var wire 5 % rs1 [4:0] $end
$var wire 32 & reg_data2 [31:0] $end
$var wire 32 ' reg_data1 [31:0] $end
$var wire 5 ( rd [4:0] $end
$var wire 7 ) opcode [6:0] $end
$var wire 32 * next_pc [31:0] $end
$var wire 32 + instruction [31:0] $end
$var wire 32 , immediate [31:0] $end
$var wire 7 - funct7 [6:0] $end
$var wire 3 . funct3 [2:0] $end
$var wire 1 / ctrl_RegWrite $end
$var wire 1 0 ctrl_Jump $end
$var wire 1 1 ctrl_ALUSrc $end
$var wire 32 2 alu_result [31:0] $end
$var wire 32 3 alu_operand_b [31:0] $end
$var wire 4 4 alu_control [3:0] $end
$var reg 32 5 pc [31:0] $end
$scope module alu_unit $end
$var wire 32 6 b [31:0] $end
$var wire 1 7 zero $end
$var wire 4 8 alu_ctrl [3:0] $end
$var wire 32 9 a [31:0] $end
$var reg 32 : result [31:0] $end
$upscope $end
$scope module aluctrl_unit $end
$var wire 3 ; funct3 [2:0] $end
$var wire 7 < funct7 [6:0] $end
$var wire 7 = opcode [6:0] $end
$var reg 4 > alu_ctrl_out [3:0] $end
$upscope $end
$scope module ctrl_unit $end
$var wire 7 ? opcode [6:0] $end
$var reg 1 1 ALUSrc $end
$var reg 1 0 Jump $end
$var reg 1 / RegWrite $end
$upscope $end
$scope module imem_unit $end
$var wire 32 @ addr [31:0] $end
$var wire 32 A instruction [31:0] $end
$upscope $end
$scope module immgen_unit $end
$var wire 32 B instruction [31:0] $end
$var wire 7 C opcode [6:0] $end
$var wire 3 D funct3 [2:0] $end
$var reg 32 E imm_out [31:0] $end
$upscope $end
$scope module regf_unit $end
$var wire 1 / RegWrite $end
$var wire 1 ! clk $end
$var wire 5 F rd [4:0] $end
$var wire 5 G rs1 [4:0] $end
$var wire 5 H rs2 [4:0] $end
$var wire 32 I write_data [31:0] $end
$var wire 32 J read_data2 [31:0] $end
$var wire 32 K read_data1 [31:0] $end
$upscope $end
$upscope $end
$upscope $end
$enddefinitions $end
$comment Show the parameter values. $end
$dumpall
$end
#0
$dumpvars
b0 K
bx J
b1010 I
b1010 H
b0 G
b1 F
b1010 E
b0 D
b10011 C
b101000000000000010010011 B
b101000000000000010010011 A
b0 @
b10011 ?
b10 >
b10011 =
b0 <
b0 ;
b1010 :
b0 9
b10 8
07
b1010 6
b0 5
b10 4
b1010 3
b1010 2
11
00
1/
b0 .
b0 -
b1010 ,
b101000000000000010010011 +
b100 *
b10011 )
b1 (
b0 '
bx &
b0 %
b1010 $
b1010 #
1"
0!
$end
#5000
1!
#10000
0!
0"
#15000
b10100 #
b10100 I
b10100 2
b10100 :
b10100 3
b10100 6
b10100 ,
b10100 E
b10100 $
b10100 H
b10 (
b10 F
b1010000000000000100010011 +
b1010000000000000100010011 A
b1010000000000000100010011 B
b1000 *
b100 5
b100 @
1!
#20000
0!
#25000
b11110 #
b11110 I
b11110 2
b11110 :
b11110 3
b11110 6
b11110 ,
b11110 E
b11110 $
b11110 H
b11 (
b11 F
b1111000000000000110010011 +
b1111000000000000110010011 A
b1111000000000000110010011 B
b1100 *
b1000 5
b1000 @
1!
#30000
0!
#35000
b101000 #
b101000 I
b101000 2
b101000 :
b11110 &
b11110 J
b1010 '
b1010 9
b1010 K
01
1/
b0 ,
b0 E
b110011 C
b11 $
b11 H
b1 %
b1 G
b110011 )
b110011 =
b110011 ?
b1100001000000110110011 +
b1100001000000110110011 A
b1100001000000110110011 B
b10000 *
b1100 5
b1100 @
1!
#40000
0!
#45000
17
b0 #
b0 I
b0 2
b0 :
b110 4
b110 8
b110 >
b10100 '
b10100 9
b10100 K
b10100 3
b10100 6
b100000 -
b100000 <
b10 $
b10 H
b10 %
b10 G
b100 (
b100 F
b10100 &
b10100 J
b1000000001000010000001000110011 +
b1000000001000010000001000110011 A
b1000000001000010000001000110011 B
b10100 *
b10000 5
b10000 @
1!
#50000
0!
#55000
b101000 '
b101000 9
b101000 K
b111 4
b111 8
b111 >
b10 D
b0 -
b0 <
b11 %
b11 G
b10 .
b10 ;
b101 (
b101 F
b1000011010001010110011 +
b1000011010001010110011 A
b1000011010001010110011 B
b11000 *
b10100 5
b10100 @
1!
#60000
0!
#65000
b1 #
b1 I
b101000 3
b101000 6
07
b1 2
b1 :
b101000 &
b101000 J
b1010 '
b1010 9
b1010 K
b11 $
b11 H
b1 %
b1 G
b110 (
b110 F
b1100001010001100110011 +
b1100001010001100110011 A
b1100001010001100110011 B
b11100 *
b11000 5
b11000 @
1!
#70000
0!
#75000
b11100 #
b11100 I
b11100 2
b11100 :
b11100 3
b11100 6
bx &
bx J
b0 '
b0 9
b0 K
b10 4
b10 8
b10 >
11
1/
b11100 ,
b11100 E
b10011 C
b0 D
b11100 $
b11100 H
b0 %
b0 G
b0 .
b0 ;
b10011 )
b10011 =
b10011 ?
b1110000000000001100010011 +
b1110000000000001100010011 A
b1110000000000001100010011 B
b100000 *
b11100 5
b11100 @
1!
#80000
0!
#85000
b1111 #
b1111 I
b1111 2
b1111 :
b1111 3
b1111 6
b1111 ,
b1111 E
b1111 $
b1111 H
b1000 (
b1000 F
b111100000000010000010011 +
b111100000000010000010011 A
b111100000000010000010011 B
b100100 *
b100000 5
b100000 @
1!
#90000
0!
#95000
bx #
bx I
x7
bx 2
bx :
b1111 &
b1111 J
bx '
bx 9
bx K
b110 4
b110 8
b110 >
01
1/
b0 ,
b0 E
b110011 C
b100000 -
b100000 <
b1000 $
b1000 H
b111 %
b111 G
b1001 (
b1001 F
b110011 )
b110011 =
b110011 ?
b1000000100000111000010010110011 +
b1000000100000111000010010110011 A
b1000000100000111000010010110011 B
b101000 *
b100100 5
b100100 @
1!
#100000
0!
#105000
b1111 #
b1111 I
07
b1111 2
b1111 :
bx &
bx J
b1111 '
b1111 9
b1111 K
b1 4
b1 8
b1 >
11
1/
b1111 ,
b1111 E
b10011 C
b110 D
b0 -
b0 <
b1111 $
b1111 H
b1000 %
b1000 G
b110 .
b110 ;
b1010 (
b1010 F
b10011 )
b10011 =
b10011 ?
b111101000110010100010011 +
b111101000110010100010011 A
b111101000110010100010011 B
b101100 *
b101000 5
b101000 @
1!
#110000
0!
#115000
b0 4
b0 8
b0 >
b111 D
b111 .
b111 ;
b1100 (
b1100 F
b111101000111011000010011 +
b111101000111011000010011 A
b111101000111011000010011 B
b110000 *
b101100 5
b101100 @
1!
#120000
0!
#125000
b0x #
b0x I
x7
b0x 2
b0x :
b1010 3
b1010 6
b1111 &
b1111 J
bx '
bx 9
bx K
b111 4
b111 8
b111 >
b1010 ,
b1010 E
b10 D
b1010 $
b1010 H
b1001 %
b1001 G
b10 .
b10 ;
b1101 (
b1101 F
b101001001010011010010011 +
b101001001010011010010011 A
b101001001010011010010011 B
b110100 *
b110000 5
b110000 @
1!
#130000
0!
#135000
17
b0 2
b0 :
b111000 #
b111000 I
b1111 3
b1111 6
b0 '
b0 9
b0 K
b1111 4
b1111 8
b1111 >
10
01
1/
b1000 ,
b1000 E
b1101111 C
b0 D
b1000 $
b1000 H
b0 %
b0 G
b0 .
b0 ;
b0 (
b0 F
b1101111 )
b1101111 =
b1101111 ?
b100000000000000001101111 +
b100000000000000001101111 A
b100000000000000001101111 B
b111000 *
b110100 5
b110100 @
1!
#140000
0!
#145000
07
b10 2
b10 :
b10 3
b10 6
b10100 &
b10100 J
b10 4
b10 8
b10 >
11
00
1/
b10 ,
b10 E
b10011 C
b10 $
b10 H
b1011 (
b1011 F
b10011 )
b10011 =
b10011 ?
b10 #
b10 I
b1000000000010110010011 +
b1000000000010110010011 A
b1000000000010110010011 B
b1000000 *
b111100 5
b111100 @
1!
#150000
0!
#155000
b1100 #
b1100 I
b1100 2
b1100 :
b1100 3
b1100 6
b1111 &
b1111 J
b1100 ,
b1100 E
b1100 $
b1100 H
b1100 (
b1100 F
b110000000000011000010011 +
b110000000000011000010011 A
b110000000000011000010011 B
b1000100 *
b1000000 5
b1000000 @
1!
#160000
0!
#165000
b0 #
b0 I
17
b0 2
b0 :
bx 3
bx 6
bx '
bx 9
bx K
b1111 4
b1111 8
b1111 >
01
0/
b0 ,
b0 E
bx C
bx D
bx -
bx <
bx $
bx H
bx %
bx G
bx .
bx ;
bx (
bx F
bx )
bx =
bx ?
bx &
bx J
bx +
bx A
bx B
b1001000 *
b1000100 5
b1000100 @
1!
#170000
0!
#175000
b1001100 *
b1001000 5
b1001000 @
1!
#180000
0!
#185000
b1010000 *
b1001100 5
b1001100 @
1!
#190000
0!
#195000
b1010100 *
b1010000 5
b1010000 @
1!
#200000
0!
#205000
b1011000 *
b1010100 5
b1010100 @
1!
#210000
0!
#215000
b1011100 *
b1011000 5
b1011000 @
1!
#220000
0!
#225000
b1100000 *
b1011100 5
b1011100 @
1!
#230000
0!
#235000
b1100100 *
b1100000 5
b1100000 @
1!
#240000
0!
#245000
b1101000 *
b1100100 5
b1100100 @
1!
#250000
0!
#255000
b1101100 *
b1101000 5
b1101000 @
1!
#260000
0!
#265000
b1110000 *
b1101100 5
b1101100 @
1!
#270000
0!
#275000
b1110100 *
b1110000 5
b1110000 @
1!
#280000
0!
#285000
b1111000 *
b1110100 5
b1110100 @
1!
#290000
0!
#295000
b1111100 *
b1111000 5
b1111000 @
1!
#300000
0!
#305000
b10000000 *
b1111100 5
b1111100 @
1!
